covimath/__init__.py
covimath/__main__.py
covimath/models/__init__.py
covimath/models/seir.py
covimath/models/seird.py
covimath/models/sir.py
covimath/models/sis.py
covimath/paramest/__init__.py
covimath/paramest/sirparams.py
covimath/tests/__init__.py
covimath/tests/test_seir.py
covimath/tests/test_seird.py
covimath/tests/test_sir.py
covimath/tests/test_sirparams.py
covimath/tests/test_sis.py
covimath/utils/__init__.py
covimath/utils/modelargs.py
covimath-0.1.2.dist-info/LICENSE
covimath-0.1.2.dist-info/METADATA
covimath-0.1.2.dist-info/WHEEL
covimath-0.1.2.dist-info/entry_points.txt
covimath-0.1.2.dist-info/top_level.txt
covimath-0.1.2.dist-info/RECORD
