Metadata-Version: 2.1
Name: covimath
Version: 0.1.2
Summary: Some mathematical models on epidemiology / Covid-19 infections
Home-page: https://github.com/techyugadi/covimath
Author: TechYugadi
Author-email: techyugadi@gmail.com
License: MIT
Download-URL: https://github.com/techyugadi/covimath/archive/refs/tags/v0.1.2.tar.gz
Platform: UNKNOWN
Classifier: License :: OSI Approved :: MIT License
Classifier: Programming Language :: Python :: 3
Classifier: Programming Language :: Python :: 3.6
Requires-Dist: numpy
Requires-Dist: scipy
Requires-Dist: matplotlib
